creevey/__init__.py
creevey/_version.py
creevey/constants.py
creevey/load_funcs/__init__.py
creevey/load_funcs/image.py
creevey/load_funcs/load_funcs.py
creevey/ops/__init__.py
creevey/ops/helpers/__init__.py
creevey/ops/helpers/report.py
creevey/ops/image/__init__.py
creevey/ops/image/stats.py
creevey/ops/image/transforms.py
creevey/path_funcs/__init__.py
creevey/path_funcs/path_funcs.py
creevey/pipelines/__init__.py
creevey/pipelines/image.py
creevey/pipelines/pipelines.py
creevey/util/__init__.py
creevey/util/image.py
creevey/util/util.py
creevey/write_funcs/__init__.py
creevey/write_funcs/image.py
tests/__init__.py
tests/conftest.py
tests/fixtures/__init__.py
tests/fixtures/image.py
tests/fixtures/misc.py
tests/test_ops/__init__.py
tests/test_ops/test_helpers/__init__.py
tests/test_ops/test_helpers/test_report.py
tests/test_ops/test_image/__init__.py
tests/test_ops/test_image/test_stats.py
tests/test_ops/test_image/test_transforms.py
creevey-2.3.0.dist-info/LICENSE.txt
creevey-2.3.0.dist-info/METADATA
creevey-2.3.0.dist-info/WHEEL
creevey-2.3.0.dist-info/top_level.txt
creevey-2.3.0.dist-info/RECORD
