Metadata-Version: 2.1
Name: creevey
Version: 2.3.0
Summary: Bulk image processing
Home-page: https://github.com/ShopRunner/creevey
Author: Greg Gandenberger
Author-email: gsganden@gmail.com
License: UNKNOWN
Download-URL: https://github.com/ShopRunner/creevey/tarball/2.3.0
Platform: UNKNOWN
Requires-Dist: boto3
Requires-Dist: joblib
Requires-Dist: opencv-contrib-python
Requires-Dist: pandas
Requires-Dist: pillow
Requires-Dist: requests
Requires-Dist: retrying
Requires-Dist: scikit-learn
Requires-Dist: tqdm
Provides-Extra: dev
Requires-Dist: boto3 ; extra == 'dev'
Requires-Dist: joblib ; extra == 'dev'
Requires-Dist: opencv-contrib-python ; extra == 'dev'
Requires-Dist: pandas ; extra == 'dev'
Requires-Dist: pillow ; extra == 'dev'
Requires-Dist: requests ; extra == 'dev'
Requires-Dist: retrying ; extra == 'dev'
Requires-Dist: scikit-learn ; extra == 'dev'
Requires-Dist: tqdm ; extra == 'dev'
Requires-Dist: black ; extra == 'dev'
Requires-Dist: flake8 ; extra == 'dev'
Requires-Dist: flake8-docstrings ; extra == 'dev'
Requires-Dist: flake8-import-order ; extra == 'dev'
Requires-Dist: matplotlib ; extra == 'dev'
Requires-Dist: pytest ; extra == 'dev'
Requires-Dist: pytest-cov ; extra == 'dev'
Requires-Dist: responses ; extra == 'dev'
